videoclipper/__init__.py
videoclipper/version.py
videoclipper/videoclipper.py
videoclipper-0.0.2.dist-info/METADATA
videoclipper-0.0.2.dist-info/WHEEL
videoclipper-0.0.2.dist-info/entry_points.txt
videoclipper-0.0.2.dist-info/top_level.txt
videoclipper-0.0.2.dist-info/RECORD
