Metadata-Version: 2.1
Name: videoclipper
Version: 0.0.2
Requires-Python: >=3.6
Requires-Dist: argparse
